android_dumpkey-0.1.2.data/scripts/dumppublickey
dumpkey/__init__.py
dumpkey/dumppublickey.py
android_dumpkey-0.1.2.dist-info/LICENSE
android_dumpkey-0.1.2.dist-info/METADATA
android_dumpkey-0.1.2.dist-info/WHEEL
android_dumpkey-0.1.2.dist-info/top_level.txt
android_dumpkey-0.1.2.dist-info/RECORD
